pdmr/__init__.py
pdmr/core.py
pdmr/exceptions.py
pdmr/utils.py
pdmr-0.1.0.dist-info/METADATA
pdmr-0.1.0.dist-info/WHEEL
pdmr-0.1.0.dist-info/top_level.txt
pdmr-0.1.0.dist-info/RECORD
