Metadata-Version: 2.1
Name: pdmr
Version: 0.1.0
Summary: pdmr: Pandas Multiprocess Runner - A library for running functions on Pandas DataFrames with multiprocessing and checkpointing.
Home-page: https://github.com/t3bol90/pdmr
Author: Toan Doan
Author-email: toandoan261120@gmail.com
Classifier: Programming Language :: Python :: 3
Classifier: License :: OSI Approved :: MIT License
Classifier: Operating System :: OS Independent
Requires-Python: >=3.8
Requires-Dist: pandas>=1.3.0
Requires-Dist: tqdm>=4.60.0
